zelus/__init__.py
zelus/cli.py
zelus/core.py
zelus_route_manager-0.2.6.dist-info/LICENSE
zelus_route_manager-0.2.6.dist-info/METADATA
zelus_route_manager-0.2.6.dist-info/WHEEL
zelus_route_manager-0.2.6.dist-info/entry_points.txt
zelus_route_manager-0.2.6.dist-info/top_level.txt
zelus_route_manager-0.2.6.dist-info/RECORD
