Metadata-Version: 2.1
Name: zelus-route-manager
Version: 0.2.6
Summary: Monitor and enforce routes.
Author-email: Mark Farrell <mark.andrew.farrell@gmail.com>
Maintainer-email: Mark Farrell <mark.andrew.farrell@gmail.com>
License: MIT License
Project-URL: Homepage, https://github.com/markafarrell/zelus/
Project-URL: Bug Reports, https://github.com/markafarrell/zelus/issues
Project-URL: Source, https://github.com/markafarrell/zelus
Classifier: Intended Audience :: Developers
Classifier: License :: OSI Approved :: MIT License
Requires-Python: >=3.7
License-File: LICENSE
Requires-Dist: pyroute2
Requires-Dist: argparse
Requires-Dist: pyaml
Requires-Dist: watchdog
Requires-Dist: jinja2
Requires-Dist: prometheus-client
Provides-Extra: dev
Requires-Dist: check-manifest; extra == "dev"
Provides-Extra: test
Requires-Dist: coverage; extra == "test"
